daqview/__init__.py
daqview/__main__.py
daqview/daqview.svg
daqview/models/__init__.py
daqview/models/channel.py
daqview/models/curve_fit.py
daqview/models/dataset.py
daqview/models/fft_channel.py
daqview/models/file_dataset.py
daqview/models/live_dataset.py
daqview/models/measurements.py
daqview/models/plot_channel.py
daqview/models/preferences.py
daqview/models/profile_dataset.py
daqview/models/readout_channel.py
daqview/models/sequencing.py
daqview/models/server.py
daqview/models/units.py
daqview/tests/__init__.py
daqview/tests/conftest.py
daqview/tests/mock_file.py
daqview/tests/mock_layout.py
daqview/tests/mock_layout.yml
daqview/tests/mock_server.py
daqview/tests/sequence_template.yml
daqview/tests/test_create_derived_channel_dialog.py
daqview/tests/test_file_dataset.py
daqview/tests/test_file_tab.py
daqview/tests/test_live_dataset.py
daqview/tests/test_live_tab.py
daqview/tests/test_main_window.py
daqview/tests/test_plot_channel.py
daqview/tests/test_plot_viewbox.py
daqview/tests/test_plot_window.py
daqview/tests/test_preferences.py
daqview/tests/test_readout_channel.py
daqview/tests/test_readout_window.py
daqview/tests/test_sequence_generator_dialog.py
daqview/tests/test_sequencing_profiles.py
daqview/tests/test_server.py
daqview/tests/test_tab_dock.py
daqview/tests/test_units.py
daqview/views/__init__.py
daqview/views/about_dialog.py
daqview/views/channel_list.py
daqview/views/create_derived_channel_dialog.py
daqview/views/fft_menus.py
daqview/views/fft_viewbox.py
daqview/views/fft_window.py
daqview/views/file_metadata.py
daqview/views/main_window.py
daqview/views/plot_cursor.py
daqview/views/plot_hover_box.py
daqview/views/plot_legend.py
daqview/views/plot_menus.py
daqview/views/plot_region.py
daqview/views/plot_viewbox.py
daqview/views/plot_window.py
daqview/views/readout_menus.py
daqview/views/readout_window.py
daqview/views/sequence_generator_dialog.py
daqview/views/sequence_load_dialog.py
daqview/views/sequence_view_dialog.py
daqview/views/tab.py
daqview-0.8.1.dist-info/METADATA
daqview-0.8.1.dist-info/WHEEL
daqview-0.8.1.dist-info/entry_points.txt
daqview-0.8.1.dist-info/licenses/COPYING
daqview-0.8.1.dist-info/RECORD
