Metadata-Version: 2.4
Name: daqview
Version: 0.8.1
Summary: DAQ Data Analysis Software
Project-URL: homepage, https://www.ael.co.uk/pages/daqview.html
Author-email: Adam Greig <adam@ael.co.uk>
License-Expression: GPL-3.0-only
License-File: COPYING
Classifier: Environment :: X11 Applications :: Qt
Classifier: Intended Audience :: Science/Research
Classifier: Topic :: Scientific/Engineering :: Visualization
Requires-Python: >=3.10
Requires-Dist: colour~=0.1
Requires-Dist: h5py~=3.6
Requires-Dist: importlib-resources~=6.5
Requires-Dist: numexpr~=2.11
Requires-Dist: numpy~=2.0
Requires-Dist: platformdirs~=4.2
Requires-Dist: pyqtgraph~=0.13
Requires-Dist: pyside6<6.9.1,>=6.8
Requires-Dist: pyyaml~=6.0
Requires-Dist: scipy~=1.15
